dlpt/__init__.py
dlpt/importer.py
dlpt/json.py
dlpt/log.py
dlpt/print_file_callables.py
dlpt/proc.py
dlpt/pth.py
dlpt/time.py
dlpt/utils.py
dlpt-3.0.0.dist-info/LICENSE
dlpt-3.0.0.dist-info/METADATA
dlpt-3.0.0.dist-info/WHEEL
dlpt-3.0.0.dist-info/top_level.txt
dlpt-3.0.0.dist-info/RECORD
