Metadata-Version: 2.1
Name: dlpt
Version: 3.0.0
Summary: Damogran Labs Python Tools
Home-page: https://github.com/damogranlabs/dlpt
Author: Damogran Labs
Author-email: info@damogranlabs.com
License: UNKNOWN
Project-URL: Documentation, https://dlpt.readthedocs.io/en/latest/
Platform: UNKNOWN
Classifier: Programming Language :: Python :: 3
Classifier: License :: OSI Approved :: MIT License
Classifier: Operating System :: OS Independent
Requires-Python: >=3.6
License-File: LICENSE
Requires-Dist: jsonpickle
Requires-Dist: psutil
